limitless/__init__.py
limitless/api_requestor.py
limitless/http_methods.py
limitless/limitless_object.py
limitless/limitless_response.py
limitless/util.py
limitless/api_endpoints/__init__.py
limitless/api_endpoints/game.py
limitless/api_endpoints/tournament.py
limitless/api_resources/__init__.py
limitless/api_resources/game.py
limitless/api_resources/tournament.py
limitless/api_resources/abstract/__init__.py
limitless/api_resources/abstract/api_resource.py
limitless/api_resources/abstract/listable_api_resource.py
limitless_python-1.1.0.dist-info/licenses/LICENSE
limitless_python-1.1.0.dist-info/METADATA
limitless_python-1.1.0.dist-info/WHEEL
limitless_python-1.1.0.dist-info/top_level.txt
limitless_python-1.1.0.dist-info/RECORD
