Metadata-Version: 2.4
Name: limitless-python
Version: 1.1.0
Home-page: https://github.com/jpbullalayao/limitless-python
Author: Professor Ragna
Author-email: professor.ragna@gmail.com
License: MIT
Classifier: Programming Language :: Python :: 3
Classifier: License :: OSI Approved :: MIT License
Classifier: Operating System :: OS Independent
License-File: LICENSE
Requires-Dist: requests
Dynamic: author
Dynamic: author-email
Dynamic: classifier
Dynamic: description
Dynamic: home-page
Dynamic: license
Dynamic: license-file
Dynamic: requires-dist
